rheia/__init__.py
rheia/CASES/__init__.py
rheia/CASES/determine_stoch_des_space.py
rheia/CASES/DATA/climate/climate_Brussels.CSV
rheia/CASES/DATA/climate/climate_Madrid.CSV
rheia/CASES/DATA/climate/climate_Paris.CSV
rheia/CASES/DATA/demand/load_Brussels_dwelling.csv
rheia/CASES/DATA/demand/load_Madrid_dwelling.csv
rheia/CASES/DATA/demand/load_Paris_dwelling.csv
rheia/CASES/ENERGYPLAN/__init__.py
rheia/CASES/ENERGYPLAN/case.txt
rheia/CASES/ENERGYPLAN/case_description.py
rheia/CASES/ENERGYPLAN/design_space.csv
rheia/CASES/ENERGYPLAN/run_energyplan.py
rheia/CASES/ENERGYPLAN/stochastic_space.csv
rheia/CASES/FOUR_BAR_TRUSS/__init__.py
rheia/CASES/FOUR_BAR_TRUSS/case_description.py
rheia/CASES/FOUR_BAR_TRUSS/design_space.csv
rheia/CASES/FOUR_BAR_TRUSS/four_bar_truss.py
rheia/CASES/FOUR_BAR_TRUSS/stochastic_space.csv
rheia/CASES/H2_FUEL/__init__.py
rheia/CASES/H2_FUEL/case_description.py
rheia/CASES/H2_FUEL/design_space.csv
rheia/CASES/H2_FUEL/design_space_tutorial_0.csv
rheia/CASES/H2_FUEL/design_space_tutorial_1.csv
rheia/CASES/H2_FUEL/design_space_tutorial_10.csv
rheia/CASES/H2_FUEL/design_space_tutorial_11.csv
rheia/CASES/H2_FUEL/design_space_tutorial_12.csv
rheia/CASES/H2_FUEL/design_space_tutorial_13.csv
rheia/CASES/H2_FUEL/design_space_tutorial_14.csv
rheia/CASES/H2_FUEL/design_space_tutorial_15.csv
rheia/CASES/H2_FUEL/design_space_tutorial_16.csv
rheia/CASES/H2_FUEL/design_space_tutorial_17.csv
rheia/CASES/H2_FUEL/design_space_tutorial_18.csv
rheia/CASES/H2_FUEL/design_space_tutorial_19.csv
rheia/CASES/H2_FUEL/design_space_tutorial_2.csv
rheia/CASES/H2_FUEL/design_space_tutorial_3.csv
rheia/CASES/H2_FUEL/design_space_tutorial_4.csv
rheia/CASES/H2_FUEL/design_space_tutorial_5.csv
rheia/CASES/H2_FUEL/design_space_tutorial_6.csv
rheia/CASES/H2_FUEL/design_space_tutorial_7.csv
rheia/CASES/H2_FUEL/design_space_tutorial_8.csv
rheia/CASES/H2_FUEL/design_space_tutorial_9.csv
rheia/CASES/H2_FUEL/design_space_tutorial_uq.csv
rheia/CASES/H2_FUEL/h2_fuel.py
rheia-1.1.13.dist-info/LICENSE
rheia-1.1.13.dist-info/METADATA
rheia-1.1.13.dist-info/WHEEL
rheia-1.1.13.dist-info/top_level.txt
rheia-1.1.13.dist-info/RECORD
